tkinterDnD/__init__.py
tkinterDnD/constants.py
tkinterDnD/dnd.py
tkinterDnD/hook.py
tkinterDnD/tk.py
tkinterDnD/linux/libtkdnd2.9.2.so
tkinterDnD/linux/pkgIndex.tcl
tkinterDnD/linux/tkdnd.tcl
tkinterDnD/linux/tkdnd_compat.tcl
tkinterDnD/linux/tkdnd_generic.tcl
tkinterDnD/linux/tkdnd_unix.tcl
tkinterDnD/linux/tkdnd_utils.tcl
tkinterDnD/mac/libtkdnd2.9.2.dylib
tkinterDnD/mac/pkgIndex.tcl
tkinterDnD/mac/tkdnd.tcl
tkinterDnD/mac/tkdnd_compat.tcl
tkinterDnD/mac/tkdnd_generic.tcl
tkinterDnD/mac/tkdnd_macosx.tcl
tkinterDnD/mac/tkdnd_utils.tcl
tkinterDnD/windows/libtkdnd2.9.2.dll
tkinterDnD/windows/pkgIndex.tcl
tkinterDnD/windows/tkdnd.tcl
tkinterDnD/windows/tkdnd2.9.2.lib
tkinterDnD/windows/tkdnd_compat.tcl
tkinterDnD/windows/tkdnd_generic.tcl
tkinterDnD/windows/tkdnd_utils.tcl
tkinterDnD/windows/tkdnd_windows.tcl
python_tkdnd-0.2.1.dist-info/LICENSE
python_tkdnd-0.2.1.dist-info/METADATA
python_tkdnd-0.2.1.dist-info/WHEEL
python_tkdnd-0.2.1.dist-info/top_level.txt
python_tkdnd-0.2.1.dist-info/RECORD
