Metadata-Version: 2.1
Name: python-tkdnd
Version: 0.2.1
Summary: Native drag & drop capabilities in tkinter. The tkinterDnD package is a nice and easy-to-use wrapper around the tkdnd tcl package.
Home-page: https://github.com/rdbende/tkinterDnD
Author: rdbende
Author-email: rdbende@gmail.com
License: MIT license
Platform: UNKNOWN
Classifier: Programming Language :: Python :: 3.6
Classifier: License :: OSI Approved :: MIT License
Classifier: Operating System :: OS Independent
Requires-Python: >=3.6
